odoo_backup_manager-1.5.21.dist-info/licenses/LICENSE
odoo_backup_tool/__init__.py
odoo_backup_tool/cli.py
odoo_backup_tool/gui_launcher.py
odoo_backup_tool/core/__init__.py
odoo_backup_tool/core/backup_restore.py
odoo_backup_tool/db/__init__.py
odoo_backup_tool/db/connection_manager.py
odoo_backup_tool/gui/__init__.py
odoo_backup_tool/gui/main_window.py
odoo_backup_tool/gui/dialogs/__init__.py
odoo_backup_tool/gui/dialogs/connection_dialog.py
odoo_backup_tool/gui/dialogs/progress_dialog.py
odoo_backup_tool/gui/widgets/__init__.py
odoo_backup_tool/utils/__init__.py
odoo_backup_tool/utils/config.py
odoo_backup_manager-1.5.21.dist-info/METADATA
odoo_backup_manager-1.5.21.dist-info/WHEEL
odoo_backup_manager-1.5.21.dist-info/entry_points.txt
odoo_backup_manager-1.5.21.dist-info/top_level.txt
odoo_backup_manager-1.5.21.dist-info/RECORD
