Metadata-Version: 2.4
Name: odoo-backup-manager
Version: 1.5.21
Summary: A comprehensive backup and restore utility for Odoo instances
Home-page: https://github.com/jpsteil/odoo-backup-manager
Author: Jim Steil
Author-email: Jim Steil <jim@steilonline.com>
License: MIT
Project-URL: Homepage, https://github.com/jpsteil/odoo-backup-manager
Project-URL: Documentation, https://github.com/jpsteil/odoo-backup-manager#readme
Project-URL: Bug Tracker, https://github.com/jpsteil/odoo-backup-manager/issues
Project-URL: Repository, https://github.com/jpsteil/odoo-backup-manager
Keywords: odoo,backup,restore,database,postgresql
Classifier: Development Status :: 4 - Beta
Classifier: Intended Audience :: System Administrators
Classifier: Topic :: System :: Archiving :: Backup
Classifier: Programming Language :: Python :: 3
Classifier: Programming Language :: Python :: 3.8
Classifier: Programming Language :: Python :: 3.9
Classifier: Programming Language :: Python :: 3.10
Classifier: Programming Language :: Python :: 3.11
Classifier: Programming Language :: Python :: 3.12
Classifier: Operating System :: OS Independent
Requires-Python: >=3.8
License-File: LICENSE
Requires-Dist: cryptography>=41.0.0
Requires-Dist: paramiko>=3.0.0
Provides-Extra: dev
Requires-Dist: pytest>=7.0.0; extra == "dev"
Requires-Dist: pytest-cov>=4.0.0; extra == "dev"
Requires-Dist: black>=23.0.0; extra == "dev"
Requires-Dist: flake8>=6.0.0; extra == "dev"
Requires-Dist: mypy>=1.0.0; extra == "dev"
Requires-Dist: build>=0.10.0; extra == "dev"
Requires-Dist: twine>=4.0.0; extra == "dev"
Dynamic: author
Dynamic: home-page
Dynamic: license-file
Dynamic: requires-python
